au_notebook.py
au_notebook-0.0.3.data/scripts/au_notebook.py
au_notebook-0.0.3.dist-info/LICENSE
au_notebook-0.0.3.dist-info/METADATA
au_notebook-0.0.3.dist-info/WHEEL
au_notebook-0.0.3.dist-info/top_level.txt
au_notebook-0.0.3.dist-info/RECORD
