Metadata-Version: 2.1
Name: au-notebook
Version: 0.0.3
Summary: 
Home-page: https://github.com/archivesunleashed/au_notebook
Author: Ryan Deschamps, Nick Ruest
Author-email: ryan.deschamps@gmail.com, ruestn@gmail.com
License: Apache 2.0
Platform: POSIX
Classifier: License :: OSI Approved :: Apache Software License
Classifier: Intended Audience :: Developers
Classifier: Topic :: Software Development :: Libraries :: Python Modules
Classifier: Topic :: Utilities
Classifier: Programming Language :: Python :: 3.7
Requires-Dist: matplotlib
Requires-Dist: networkx
Requires-Dist: nltk
Requires-Dist: numpy
Requires-Dist: pandas
